setup.py
rl_distributions/Binomialdistribution.py
rl_distributions/Gaussiandistribution.py
rl_distributions/Generaldistribution.py
rl_distributions/__init__.py
rl_distributions/test.py
rl_distributions.egg-info/PKG-INFO
rl_distributions.egg-info/SOURCES.txt
rl_distributions.egg-info/dependency_links.txt
rl_distributions.egg-info/not-zip-safe
rl_distributions.egg-info/top_level.txt